gridforge/__init__.py
gridforge/builder.py
gridforge/data_validator.py
gridforge/export_manager.py
gridforge/input_handler.py
gridforge/style_manager.py
gridforge/table_generator.py
gridforge/type_formatter.py
gridforge-3.0.0.dist-info/licenses/LICENSE
gridforge-3.0.0.dist-info/METADATA
gridforge-3.0.0.dist-info/WHEEL
gridforge-3.0.0.dist-info/top_level.txt
gridforge-3.0.0.dist-info/RECORD
