Metadata-Version: 2.4
Name: gridforge
Version: 3.0.0
Summary: Eine extrem schnelle und moderne Python-Bibliothek zur Erstellung von gut formatierten Tabellen in der Konsole
Home-page: https://github.com/yourusername/gridforge
Author: Your Name
Author-email: Your Name <your.email@example.com>
License: MIT
Project-URL: Homepage, https://github.com/yourusername/gridforge
Project-URL: Documentation, https://github.com/yourusername/gridforge#readme
Project-URL: Repository, https://github.com/yourusername/gridforge
Project-URL: Issues, https://github.com/yourusername/gridforge/issues
Keywords: console,table,terminal,cli,formatting,display,rich,pandas,performance,fast
Classifier: Development Status :: 4 - Beta
Classifier: Intended Audience :: Developers
Classifier: Topic :: Software Development :: Libraries :: Python Modules
Classifier: Topic :: Text Processing :: Markup
Classifier: License :: OSI Approved :: MIT License
Classifier: Programming Language :: Python :: 3
Classifier: Programming Language :: Python :: 3.7
Classifier: Programming Language :: Python :: 3.8
Classifier: Programming Language :: Python :: 3.9
Classifier: Programming Language :: Python :: 3.10
Classifier: Programming Language :: Python :: 3.11
Classifier: Programming Language :: Python :: 3.12
Classifier: Operating System :: OS Independent
Requires-Python: >=3.7
License-File: LICENSE
Requires-Dist: rich>=13.0.0
Requires-Dist: pandas>=2.0.0
Provides-Extra: dev
Requires-Dist: pytest>=7.0.0; extra == "dev"
Requires-Dist: pytest-cov>=4.0.0; extra == "dev"
Requires-Dist: black>=23.0.0; extra == "dev"
Requires-Dist: flake8>=6.0.0; extra == "dev"
Dynamic: author
Dynamic: home-page
Dynamic: license-file
Dynamic: requires-python
